{
    "uuid": "521e3456-3ad5-4d25-91c2-46f0255894a0",
    "session_id": "REGISTRATION",
    "username": "wrongcert_integration",
    "email": "wrongcert_integration@example.com",
    "password_hash": "1f654fa70de4b3e2e80e6e86420aea61ca947f7cc61d58da3e32c1e04b246645",
    "salt": "c61773dfc6090c94217a15d1598aedfc",
    "public_key": [
        149,
        105,
        213,
        99,
        40,
        43,
        7,
        8,
        132,
        33,
        39,
        181,
        93,
        47,
        168,
        12,
        75,
        63,
        112,
        36,
        247,
        221,
        182,
        172,
        124,
        117,
        253,
        108,
        213,
        11,
        225,
        45,
        239,
        64,
        223,
        229,
        232,
        139,
        240,
        56,
        186,
        132,
        215,
        207,
        184,
        234,
        116,
        0,
        187,
        23,
        188,
        193,
        24,
        145,
        89,
        59,
        251,
        137,
        80,
        183,
        146,
        242,
        229,
        246,
        231,
        145,
        149,
        239,
        5,
        49,
        97,
        12,
        183,
        38,
        165,
        14,
        2,
        76,
        127,
        125,
        40,
        230,
        144,
        195,
        27,
        76,
        176,
        40,
        151,
        170,
        177,
        141,
        85,
        176,
        59,
        208,
        232,
        138,
        139,
        8,
        65,
        131,
        251,
        126,
        84,
        169,
        174,
        52,
        164,
        245,
        98,
        236,
        245,
        238,
        131,
        189,
        216,
        225,
        43,
        12,
        200,
        174,
        225,
        196,
        151,
        68,
        45,
        124,
        98,
        74,
        193,
        3,
        158,
        243,
        27,
        74,
        94,
        202,
        135,
        79,
        199,
        112,
        127,
        57,
        217,
        36,
        159,
        34,
        31,
        254,
        218,
        99,
        125,
        215,
        105,
        106,
        23,
        188,
        100,
        88,
        111,
        13,
        191,
        185,
        165,
        172,
        194,
        36,
        222,
        174,
        248,
        199,
        152,
        149,
        46,
        119,
        162,
        12,
        116,
        92,
        162,
        49,
        156,
        172,
        132,
        82,
        195,
        230,
        210,
        56,
        233,
        208,
        254,
        216,
        130,
        167,
        202,
        205,
        116,
        214,
        3,
        175,
        44,
        175,
        231,
        190,
        164,
        92,
        136,
        187,
        106,
        95,
        226,
        158,
        16,
        7,
        83,
        254,
        222,
        77,
        176,
        216,
        91,
        224,
        29,
        232,
        114,
        11,
        43,
        42,
        219,
        157,
        189,
        95,
        167,
        192,
        80,
        234,
        164,
        226,
        80,
        44,
        198,
        156,
        33,
        95,
        180,
        232,
        108,
        165,
        8,
        203,
        94,
        77,
        72,
        65,
        144,
        27,
        144,
        218,
        127,
        113,
        127,
        87,
        157,
        194,
        210,
        192,
        140,
        46,
        205,
        114,
        169,
        132,
        197,
        70,
        9,
        125,
        74,
        235,
        188,
        240,
        5,
        75,
        221,
        124,
        110,
        17,
        224,
        59,
        153,
        33,
        23,
        157,
        223,
        144,
        13,
        172,
        57,
        41,
        176,
        107,
        240,
        162,
        215,
        29,
        203,
        104,
        108,
        215,
        199,
        254,
        153,
        62,
        208,
        197,
        68,
        244,
        244,
        219,
        18,
        66,
        213,
        254,
        121,
        189,
        101,
        41,
        44,
        35,
        112,
        216,
        27,
        84,
        71,
        188,
        7,
        4,
        118,
        101,
        31,
        177,
        117,
        91,
        192,
        160,
        177,
        199,
        233,
        89,
        83,
        107,
        136,
        249,
        189,
        192,
        223,
        136,
        134,
        75,
        99,
        131,
        243,
        208,
        132,
        193,
        160,
        152,
        81,
        228,
        178,
        119,
        73,
        96,
        184,
        240,
        170,
        11,
        46,
        21,
        146,
        183,
        253,
        83,
        198,
        168,
        127,
        12,
        36,
        67,
        7,
        140,
        70,
        235,
        146,
        217,
        210,
        244,
        1,
        139,
        57,
        252,
        231,
        26,
        166,
        159,
        199,
        173,
        55,
        14,
        159,
        130,
        24,
        90,
        131,
        219,
        156,
        157,
        67,
        198,
        204,
        167,
        252,
        16,
        195,
        36,
        145,
        240,
        51,
        60,
        175,
        43,
        194,
        58,
        64,
        76,
        98,
        103,
        121,
        42,
        4,
        92,
        5,
        237,
        71,
        54,
        26,
        43,
        150,
        141,
        172,
        241,
        103,
        211,
        101,
        30,
        107,
        58,
        19,
        179,
        243,
        122,
        25,
        97,
        120,
        92,
        121,
        87,
        116,
        96,
        112,
        0,
        23,
        141,
        146,
        157,
        124,
        218,
        75,
        225,
        244,
        240,
        33,
        247,
        108,
        219,
        59,
        208,
        117,
        101,
        230,
        235,
        239,
        58,
        173,
        100,
        85,
        22,
        58,
        55,
        81,
        210,
        251,
        227,
        96,
        29,
        85,
        209,
        4,
        37,
        223,
        185,
        144,
        61,
        136,
        135,
        119,
        215,
        22,
        105,
        189,
        25,
        214,
        79,
        1,
        198,
        202,
        134,
        197,
        33,
        179,
        84,
        57,
        129,
        247,
        254,
        124,
        179,
        93,
        188,
        108,
        147,
        68,
        216,
        149,
        133,
        214,
        205,
        172,
        201,
        244,
        72,
        254,
        254,
        170,
        73,
        17,
        27,
        150,
        90,
        1,
        170,
        31,
        143,
        74,
        0,
        186,
        237,
        157,
        235,
        190,
        159,
        161,
        145,
        198,
        179,
        236,
        87,
        73,
        83,
        120,
        116,
        5,
        188,
        249,
        24,
        197,
        201,
        78,
        197,
        210,
        164,
        32,
        115,
        239,
        115,
        42,
        135,
        88,
        140,
        84,
        7,
        63,
        102,
        146,
        248,
        12,
        96,
        91,
        74,
        68,
        172,
        156,
        87,
        230,
        210,
        162,
        50,
        149,
        72,
        21,
        99,
        212,
        161,
        64,
        58,
        228,
        210,
        53,
        104,
        206,
        15,
        126,
        213,
        243,
        157,
        4,
        85,
        94,
        223,
        137,
        27,
        155,
        104,
        154,
        37,
        251,
        109,
        208,
        178,
        43,
        151,
        73,
        1,
        239,
        81,
        86,
        11,
        42,
        126,
        133,
        108,
        192,
        178,
        176,
        168,
        42,
        121,
        41,
        65,
        36,
        24,
        200,
        101,
        235,
        140,
        172,
        216,
        153,
        28,
        222,
        71,
        238,
        140,
        211,
        164,
        207,
        57,
        174,
        142,
        60,
        204,
        248,
        55,
        8,
        15,
        62,
        217,
        120,
        248,
        70,
        104,
        121,
        189,
        3,
        188,
        3,
        198,
        72,
        185,
        153,
        168,
        89,
        171,
        51,
        254,
        174,
        228,
        45,
        172,
        170,
        157,
        55,
        232,
        152,
        196,
        15,
        64,
        90,
        253,
        189,
        18,
        209,
        137,
        51,
        21,
        36,
        50,
        160,
        138,
        7,
        192,
        187,
        177,
        75,
        72,
        107,
        107,
        16,
        93,
        244,
        143,
        249,
        119,
        92,
        159,
        178,
        114,
        219,
        75,
        198,
        51,
        13,
        52,
        84,
        75,
        124,
        140,
        42,
        188,
        120,
        9,
        168,
        115,
        187,
        49,
        113,
        147,
        66,
        31,
        32,
        139,
        182,
        109,
        189,
        112,
        16,
        28,
        28,
        38,
        43,
        152,
        23,
        250,
        31,
        245,
        6,
        98,
        192,
        119,
        13,
        146,
        211,
        197,
        230,
        114,
        29,
        2,
        251,
        117,
        217,
        186,
        194,
        233,
        110,
        101,
        102,
        80,
        58,
        247,
        86,
        178,
        123,
        104,
        43,
        20,
        237,
        88,
        195,
        243,
        214,
        69,
        56,
        249,
        25,
        187,
        182,
        51,
        189,
        178,
        146,
        117,
        91,
        135,
        107,
        126,
        155,
        2,
        151,
        214,
        86,
        100,
        57,
        106,
        197,
        250,
        76,
        120,
        219,
        236,
        168,
        35,
        130,
        67,
        210,
        174,
        196,
        244,
        225,
        71,
        227,
        64,
        98,
        223,
        75,
        211,
        51,
        25,
        241,
        207,
        171,
        198,
        176,
        49,
        88,
        209,
        24,
        6,
        129,
        88,
        150,
        52,
        29,
        255,
        202,
        119,
        167,
        56,
        230,
        122,
        174,
        242,
        228,
        30,
        204,
        56,
        253,
        220,
        186,
        37,
        28,
        84,
        191,
        230,
        34,
        168,
        136,
        169,
        169,
        101,
        129,
        175,
        143,
        146,
        197,
        96,
        185,
        24,
        242,
        249,
        177,
        56,
        161,
        171,
        6,
        172,
        193,
        138,
        112,
        82,
        157,
        45,
        11,
        40,
        76,
        176,
        167,
        51,
        118,
        205,
        52,
        97,
        121,
        173,
        51,
        44,
        117,
        232,
        237,
        78,
        10,
        199,
        38,
        20,
        243,
        104,
        196,
        158,
        219,
        116,
        153,
        17,
        36,
        149,
        222,
        79,
        21,
        112,
        129,
        91,
        44,
        213,
        29,
        17,
        151,
        145,
        112,
        194,
        140,
        91,
        50,
        92,
        105,
        201,
        108,
        12,
        128,
        104,
        117,
        106,
        198,
        38,
        74,
        155,
        245,
        48,
        12,
        16,
        72,
        50,
        128,
        159,
        141,
        161,
        132,
        139,
        5,
        119,
        106,
        152,
        124,
        107,
        222,
        36,
        222,
        114,
        100,
        45,
        208,
        18,
        217,
        250,
        169,
        70,
        2,
        18,
        53,
        42,
        99,
        54,
        160,
        250,
        59,
        198,
        230,
        81,
        182,
        116,
        239,
        3,
        67,
        148,
        113,
        99,
        197,
        143,
        77,
        116,
        27,
        178,
        177,
        144,
        232,
        209,
        219,
        175,
        44,
        70,
        231,
        182,
        146,
        35,
        161,
        83,
        158,
        164,
        246,
        108,
        62,
        189,
        199,
        198,
        150,
        247,
        218,
        48,
        96,
        222,
        35,
        176,
        231,
        111,
        231,
        181,
        85,
        26,
        167,
        187,
        34,
        101,
        56,
        83,
        186,
        90,
        51,
        116,
        174,
        107,
        249,
        76,
        153,
        137,
        210,
        224,
        187,
        244,
        130,
        86,
        184,
        110,
        156,
        150,
        38,
        119,
        239,
        254,
        96,
        79,
        131,
        141,
        255,
        219,
        225,
        207,
        217,
        19,
        159,
        245,
        117,
        207,
        163,
        238,
        150,
        157,
        57,
        254,
        144,
        123,
        98,
        248,
        195,
        40,
        203,
        220,
        247,
        228,
        222,
        152,
        61,
        64,
        248,
        206,
        59,
        233,
        48,
        176,
        169,
        62,
        124,
        98,
        232,
        10,
        252,
        154,
        142,
        83,
        157,
        157,
        160,
        213,
        235,
        164,
        173,
        90,
        74,
        105,
        162,
        191,
        40,
        91,
        127,
        61,
        140,
        27,
        219,
        131,
        67,
        245,
        228,
        125,
        227,
        91,
        20,
        140,
        136,
        85,
        220,
        255,
        65,
        117,
        175,
        203,
        168,
        142,
        80,
        36,
        211,
        207,
        170,
        126,
        142,
        76,
        130,
        21,
        65,
        108,
        96,
        90,
        79,
        16,
        42,
        172,
        52,
        115,
        210,
        63,
        195,
        69,
        123,
        110,
        185,
        129,
        54,
        131,
        248,
        224,
        165,
        10,
        14,
        166,
        193,
        253,
        189,
        177,
        7,
        189,
        207,
        73,
        148,
        181,
        243,
        57,
        173,
        215,
        252,
        149,
        203,
        63,
        184,
        38,
        116,
        202,
        153,
        236,
        211,
        116,
        65,
        213,
        242,
        20,
        41,
        233,
        142,
        21,
        112,
        109,
        59,
        56,
        50,
        85,
        56,
        176,
        249,
        156,
        178,
        252,
        254,
        188,
        187,
        63,
        27,
        27,
        239,
        249,
        227,
        93,
        131,
        64,
        79,
        154,
        120,
        84,
        226,
        241,
        143,
        109,
        195,
        131,
        59,
        175,
        59,
        186,
        143,
        156,
        3,
        46,
        7,
        184,
        210,
        184,
        170,
        52,
        162,
        28,
        192,
        158,
        106,
        207,
        218,
        186,
        100,
        67,
        123,
        115,
        146,
        212,
        83,
        58,
        241,
        12,
        6,
        85,
        248,
        83,
        127,
        203,
        89,
        255,
        4,
        82,
        80,
        53,
        182,
        41,
        72,
        224,
        32,
        232,
        200,
        48,
        21,
        125,
        94,
        181,
        177,
        244,
        4,
        34,
        255,
        50,
        245,
        7,
        215,
        255,
        181,
        219,
        12,
        151,
        67,
        157,
        205,
        114,
        70,
        206,
        145,
        189,
        131,
        185,
        21,
        227,
        181,
        204,
        216,
        253,
        62,
        155,
        113,
        232,
        225,
        238,
        77,
        185,
        130,
        146,
        228,
        175,
        198,
        193,
        150,
        189,
        18,
        152,
        251,
        135,
        103,
        14,
        106,
        84,
        72,
        106,
        16,
        150,
        232,
        155,
        18,
        225,
        134,
        146,
        109,
        84,
        84,
        120,
        158,
        232,
        41,
        40,
        114,
        186,
        185,
        46,
        239,
        90,
        99,
        111,
        169,
        127,
        124,
        132,
        22,
        35,
        63,
        135,
        3,
        254,
        229,
        213,
        41,
        5,
        71,
        121,
        192,
        106,
        117,
        131,
        56,
        178,
        208,
        239,
        108,
        224,
        55,
        248,
        249,
        5,
        126,
        186,
        14,
        98,
        162,
        108,
        129,
        84,
        150,
        46,
        214,
        122,
        124,
        185,
        171,
        222,
        205,
        121,
        81,
        32,
        244,
        48,
        233,
        127,
        105,
        96,
        247,
        246,
        245,
        233,
        164,
        180,
        137,
        41,
        68,
        213,
        16,
        244,
        226,
        198,
        101,
        182,
        65,
        174,
        0,
        247,
        153,
        67,
        66,
        173,
        84,
        247,
        158,
        138,
        86,
        205,
        137,
        200,
        175,
        53,
        201,
        155,
        103,
        90,
        26,
        107,
        11,
        189,
        205,
        188,
        36,
        196,
        253,
        175,
        57,
        194,
        99,
        230,
        158,
        181,
        147,
        3,
        80,
        205,
        197,
        120,
        232,
        188,
        49,
        218,
        196,
        214,
        105,
        229,
        251,
        62,
        2,
        123,
        60,
        39,
        251,
        207,
        27,
        201,
        121,
        19,
        172,
        44,
        199,
        20,
        42,
        208,
        146,
        146,
        19,
        112,
        155,
        192,
        194,
        133,
        72,
        102,
        88,
        103,
        64,
        75,
        255,
        164,
        101,
        4,
        210,
        153,
        136,
        124,
        17,
        200,
        95,
        88,
        238,
        236,
        242,
        78,
        111,
        236,
        11,
        211,
        252,
        166,
        138,
        14,
        223,
        196,
        28,
        17,
        128,
        63,
        57,
        54,
        47,
        24,
        60,
        195,
        149,
        215,
        105,
        95,
        179,
        210,
        108,
        42,
        145,
        142,
        5,
        101,
        114,
        51,
        34,
        11,
        62,
        206,
        53,
        157,
        31,
        138,
        82,
        28,
        160,
        98,
        124,
        7,
        210,
        106,
        43,
        136,
        156,
        247,
        113,
        46,
        220,
        92,
        227,
        104,
        134,
        77,
        159,
        82,
        104,
        24,
        180,
        94,
        88,
        51,
        145,
        25,
        248,
        208,
        98,
        231,
        236,
        221,
        48,
        83,
        60,
        160,
        171,
        252,
        48,
        93,
        208,
        230,
        202,
        100,
        80,
        162,
        223,
        239,
        67,
        187,
        199,
        148,
        254,
        218,
        24,
        245,
        77,
        160,
        241,
        94,
        236,
        222,
        83,
        184,
        150,
        122,
        31,
        106,
        44,
        167,
        99,
        207,
        70,
        215,
        214,
        26,
        169,
        110,
        143,
        93,
        204,
        81,
        158,
        235,
        75,
        127,
        215,
        102,
        157,
        6,
        170,
        167,
        177,
        46,
        58,
        72,
        7,
        18,
        137,
        184,
        252,
        142,
        70,
        44,
        2,
        86,
        187,
        116,
        247,
        178,
        228,
        187,
        133,
        121,
        34,
        124,
        65,
        241,
        188,
        20,
        60,
        7,
        14,
        116,
        160,
        206,
        62,
        195,
        125,
        42,
        56,
        197,
        41,
        164,
        49,
        244,
        90,
        184,
        177,
        51,
        134,
        113,
        219,
        91,
        19,
        107,
        48,
        27,
        162,
        100,
        31,
        140,
        18,
        98,
        227,
        194,
        111,
        78,
        198,
        161,
        54,
        95,
        123,
        69,
        149,
        14,
        237,
        116,
        251,
        233,
        132,
        83,
        247,
        181,
        139,
        6,
        197,
        253,
        196,
        191,
        59,
        246,
        130,
        69,
        238,
        116,
        11,
        41,
        190,
        137,
        109,
        70,
        4,
        163,
        125,
        107,
        15,
        143,
        155,
        22,
        124,
        193,
        137,
        232,
        112,
        61,
        20,
        9,
        41,
        156,
        136,
        150,
        114,
        207,
        226,
        254,
        51,
        232,
        181,
        10,
        34,
        255,
        31,
        110,
        158,
        105,
        224,
        80,
        44,
        168,
        155,
        240,
        239,
        210,
        78,
        113,
        171,
        173,
        112,
        96,
        156,
        137,
        230,
        207,
        99,
        77,
        143,
        189,
        219,
        86,
        116,
        239,
        171,
        82,
        21,
        205,
        155,
        111,
        137,
        10,
        140,
        233,
        12,
        121,
        98,
        233,
        200,
        238,
        206,
        175,
        114,
        84,
        242,
        128,
        218,
        212,
        29,
        202,
        172,
        246,
        185,
        74,
        21,
        180,
        56,
        157,
        206,
        166,
        21,
        233,
        251,
        100,
        105,
        170,
        13,
        235,
        213,
        54,
        210,
        11,
        130,
        102,
        79,
        171,
        111,
        70,
        236,
        217,
        213,
        246,
        54,
        73,
        92,
        32,
        153,
        28,
        71,
        56,
        195,
        99,
        217,
        237,
        140,
        181,
        184,
        6,
        166,
        67,
        40,
        188,
        134,
        85,
        229,
        170,
        86,
        135,
        63,
        29,
        197,
        49,
        216,
        170,
        176,
        165,
        50,
        97,
        227,
        144,
        234,
        152,
        114,
        103,
        251,
        93,
        10,
        132,
        130,
        185,
        167,
        211,
        80,
        128,
        195,
        107,
        232,
        231,
        19,
        232,
        221,
        99,
        144,
        126,
        97,
        208,
        241,
        252,
        42,
        190,
        128,
        94,
        16,
        78,
        129,
        143,
        44,
        84,
        218,
        148,
        139,
        218,
        221,
        240,
        20,
        101,
        182,
        238,
        153,
        223,
        239,
        193,
        50,
        84,
        49,
        109,
        129,
        177,
        29,
        63,
        117,
        86,
        152,
        77,
        90,
        77,
        210,
        38,
        12,
        231,
        136,
        18,
        179,
        197,
        195,
        140,
        46,
        20,
        230,
        152,
        219,
        190,
        175,
        125,
        123,
        174,
        192,
        39,
        194,
        80,
        159,
        181,
        67,
        93,
        238,
        158,
        247,
        14,
        64,
        50,
        85,
        225,
        15,
        77,
        230,
        111,
        236,
        22,
        208,
        150,
        97,
        115,
        58,
        222,
        28,
        180,
        95,
        59,
        116,
        117,
        47,
        107,
        180,
        183,
        130,
        236,
        3,
        191,
        115,
        36,
        9,
        42,
        14,
        23,
        118,
        167,
        197,
        210,
        51,
        201,
        218,
        219,
        172,
        249,
        172,
        142,
        216,
        84,
        100,
        214,
        97,
        114,
        18,
        130,
        69,
        42,
        129,
        46,
        165,
        106,
        0,
        103,
        111,
        185,
        90,
        210,
        178,
        2,
        196,
        46,
        196,
        110,
        7,
        134,
        130,
        40,
        91,
        131,
        25,
        197,
        6,
        227,
        68,
        0,
        65,
        250,
        18,
        103,
        163,
        26,
        143,
        68,
        186,
        63,
        233,
        145,
        81,
        81,
        78,
        103,
        133,
        112,
        129,
        20,
        145,
        133,
        4,
        207,
        92,
        33,
        106,
        218,
        7,
        65,
        144,
        23,
        2,
        219,
        91,
        54,
        67,
        63,
        4,
        151,
        50,
        102,
        90,
        160,
        64,
        81,
        61,
        142,
        249,
        10,
        13,
        145,
        216,
        249,
        142,
        74,
        205,
        236,
        255,
        212,
        146,
        134,
        146,
        217,
        236,
        115,
        76,
        210,
        200,
        122,
        7,
        253,
        93,
        157,
        26,
        239,
        18,
        60,
        144,
        208,
        78,
        118,
        62,
        124,
        208,
        17,
        103,
        137,
        185,
        170,
        124,
        126,
        101,
        203,
        206,
        20,
        85,
        104,
        236,
        65,
        108,
        98,
        11,
        14,
        19,
        213,
        89,
        231,
        2,
        59,
        172,
        35,
        32,
        25,
        45,
        80,
        164,
        99,
        46,
        132,
        217,
        210,
        195,
        95,
        216,
        5,
        133,
        9,
        33,
        145,
        214,
        117,
        13,
        24,
        194,
        195,
        120,
        152,
        182,
        111,
        84,
        157,
        163,
        232,
        250,
        6,
        145,
        4,
        87,
        7,
        208,
        224,
        228,
        245,
        49,
        130,
        174,
        79,
        111,
        254,
        44,
        219,
        191,
        85,
        106,
        238,
        98,
        58,
        1,
        150,
        157,
        95,
        137,
        124,
        124,
        3,
        151,
        92,
        195,
        83,
        59,
        208,
        22,
        158,
        245,
        246,
        198,
        127,
        180,
        145,
        2,
        134,
        94,
        25,
        187,
        169,
        80,
        24,
        65,
        36,
        130,
        153,
        1,
        94,
        80,
        65,
        162,
        56,
        8,
        208,
        16,
        73,
        56,
        26,
        7,
        180,
        24,
        117,
        138,
        196,
        224,
        248,
        170,
        196,
        101,
        78,
        215,
        12,
        72,
        111,
        218,
        128,
        7,
        192,
        127,
        61,
        118,
        156,
        196,
        106,
        133,
        195,
        131,
        151,
        118,
        203,
        246,
        93,
        218,
        73,
        89,
        176,
        14,
        16,
        188,
        221,
        15,
        182,
        125,
        214,
        84,
        203,
        137,
        13,
        215,
        230,
        201,
        181,
        178,
        136,
        77,
        136,
        177,
        137,
        112,
        2,
        23,
        195,
        75,
        74,
        127,
        56,
        136,
        191,
        252,
        208,
        63,
        179,
        111,
        33,
        44,
        178,
        3,
        64,
        204,
        39,
        42,
        28,
        204,
        189,
        60,
        232,
        45,
        17,
        43,
        237,
        54,
        217,
        208,
        147,
        196,
        34,
        198,
        155,
        31,
        237,
        181,
        65,
        23,
        213,
        144,
        210,
        26,
        180,
        190,
        173,
        42,
        150,
        191,
        67,
        248,
        152,
        94,
        62,
        135,
        87,
        31,
        241,
        102,
        4,
        49,
        179,
        168,
        186,
        186,
        91,
        199,
        27,
        160,
        96,
        159,
        164,
        0,
        53,
        32,
        109,
        116,
        49,
        53,
        47,
        234,
        244,
        111,
        186,
        175,
        39,
        153,
        234,
        36,
        105,
        86,
        212,
        239,
        30,
        23,
        77,
        235,
        62,
        113,
        104,
        246,
        19,
        20,
        158,
        131,
        27,
        142,
        190
    ],
    "client_cert_fingerprint": "0f53ca7ee15b7e40c0ddc3b77dc1e2dbd6d7d866f9b4efc4d461cc6079db9ab5",
    "created_at": "2025-04-05T08:08:32.049496+00:00"
}